odoo/addons/pos_partner_sale_warning/README.rst
odoo/addons/pos_partner_sale_warning/__init__.py
odoo/addons/pos_partner_sale_warning/__manifest__.py
odoo/addons/pos_partner_sale_warning/i18n/es.po
odoo/addons/pos_partner_sale_warning/i18n/it.po
odoo/addons/pos_partner_sale_warning/i18n/pos_partner_sale_warning.pot
odoo/addons/pos_partner_sale_warning/models/__init__.py
odoo/addons/pos_partner_sale_warning/models/pos_session.py
odoo/addons/pos_partner_sale_warning/readme/CONFIGURE.md
odoo/addons/pos_partner_sale_warning/readme/CONTEXT.md
odoo/addons/pos_partner_sale_warning/readme/CONTRIBUTORS.md
odoo/addons/pos_partner_sale_warning/readme/DESCRIPTION.md
odoo/addons/pos_partner_sale_warning/readme/ROADMAP.md
odoo/addons/pos_partner_sale_warning/readme/USAGE.md
odoo/addons/pos_partner_sale_warning/static/description/icon.png
odoo/addons/pos_partner_sale_warning/static/description/index.html
odoo/addons/pos_partner_sale_warning/static/src/js/PartnerListScreen.esm.js
odoo/addons/pos_partner_sale_warning/static/src/tests/tours/PosPartnerSaleWarning.esm.js
odoo/addons/pos_partner_sale_warning/tests/__init__.py
odoo/addons/pos_partner_sale_warning/tests/test_pos_ui.py
odoo_addon_pos_partner_sale_warning-17.0.1.0.0.2.dist-info/METADATA
odoo_addon_pos_partner_sale_warning-17.0.1.0.0.2.dist-info/WHEEL
odoo_addon_pos_partner_sale_warning-17.0.1.0.0.2.dist-info/top_level.txt
odoo_addon_pos_partner_sale_warning-17.0.1.0.0.2.dist-info/RECORD
